nvidia/nvcomp/nvcomp_impl.cpython-311-aarch64-linux-gnu.so
nvidia/nvcomp/nvcomp_impl.cpython-38-aarch64-linux-gnu.so
nvidia/nvcomp/include/nvcomp/shared_types.h
nvidia/nvcomp/include/nvcomp/zstd.h
nvidia/nvcomp/include/nvcomp/gdeflate.hpp
nvidia/nvcomp/include/nvcomp/snappy.hpp
nvidia/nvcomp/include/nvcomp/gzip.h
nvidia/nvcomp/include/nvcomp/cascaded.h
nvidia/nvcomp/include/nvcomp/deflate.h
nvidia/nvcomp/include/nvcomp/bitcomp.hpp
nvidia/nvcomp/include/nvcomp/crc32.h
nvidia/nvcomp/include/nvcomp/snappy.h
nvidia/nvcomp/include/nvcomp/cascaded.hpp
nvidia/nvcomp/include/nvcomp/lz4.h
nvidia/nvcomp/include/nvcomp/deflate.hpp
nvidia/nvcomp/include/nvcomp/ans.hpp
nvidia/nvcomp/include/nvcomp/native/bitcomp.h
nvidia/nvcomp/include/nvcomp/utils.hpp
nvidia/nvcomp/include/nvcomp/nvcompManager.hpp
nvidia/nvcomp/include/nvcomp/native/gdeflate_cpu.h
nvidia/nvcomp/include/nvcomp/lz4.hpp
nvidia/nvcomp/nvcomp_impl.cpython-313-aarch64-linux-gnu.so
nvidia/nvcomp/include/nvcomp/bitcomp.h
nvidia/nvcomp/nvcomp_impl.cpython-312-aarch64-linux-gnu.so
nvidia/nvcomp/include/nvcomp/gdeflate.h
nvidia/nvcomp/include/nvcomp/zstd.hpp
nvidia/nvcomp/include/nvcomp/nvcompManagerFactory.hpp
nvidia/nvcomp/nvcomp_impl.cpython-39-aarch64-linux-gnu.so
nvidia/nvcomp/include/nvcomp.h
nvidia/nvcomp/external_memory.py
nvidia/nvcomp/include/nvcomp.hpp
nvidia/nvcomp/include/nvcomp/gzip.hpp
nvidia/nvcomp/__init__.py
nvidia_nvcomp_cu13-5.0.0.6.dist-info/NOTICE
nvidia/nvcomp/include/nvcomp/ans.h
nvidia_nvcomp_cu13-5.0.0.6.dist-info/WHEEL
nvidia/__init__.py
nvidia/nvcomp/nvcomp_impl.cpython-310-aarch64-linux-gnu.so
nvidia_nvcomp_cu13-5.0.0.6.dist-info/LICENSE
nvidia_nvcomp_cu13-5.0.0.6.dist-info/top_level.txt
nvidia_nvcomp_cu13-5.0.0.6.dist-info/METADATA
nvidia/nvcomp/libnvcomp.so.5
nvidia_nvcomp_cu13-5.0.0.6.dist-info/RECORD
